wledges/__init__.py
wledges/__main__.py
wledges/version.py
wledges/wledges.py
wledges-1.dist-info/LICENSE
wledges-1.dist-info/METADATA
wledges-1.dist-info/WHEEL
wledges-1.dist-info/entry_points.txt
wledges-1.dist-info/top_level.txt
wledges-1.dist-info/RECORD
