Metadata-Version: 2.1
Name: wledges
Version: 1
Summary: Active edges for wayland.
Author: Shaked Flur
Maintainer: Shaked Flur
Project-URL: Homepage, https://github.com/fshaked/wledges
Project-URL: Documentation, https://github.com/fshaked/wledges
Project-URL: Repository, https://github.com/fshaked/wledges.git
Project-URL: Issues, https://github.com/fshaked/wledges/issues
Project-URL: Changelog, https://github.com/fshaked/wledges/CHANGELOG.md
Keywords: edges,wayland,sway,layer-shell,wlr,wlroots
Classifier: Development Status :: 4 - Beta
Classifier: Intended Audience :: End Users/Desktop
Classifier: Intended Audience :: System Administrators
Classifier: Topic :: Desktop Environment
Classifier: Topic :: Utilities
Classifier: License :: OSI Approved :: MIT License
Classifier: Programming Language :: Python :: 3
Requires-Python: >=3.9
License-File: LICENSE
Requires-Dist: pycairo>=1.27.0
Requires-Dist: PyGObject>=3.50.0
